nepse/__init__.py
nepse/broker/__init__.py
nepse/broker/core.py
nepse/broker/decorators.py
nepse/broker/types.py
nepse/core.py
nepse/errors.py
nepse/market/__init__.py
nepse/market/core.py
nepse/market/types.py
nepse/security/__init__.py
nepse/security/core.py
nepse/security/decorators.py
nepse/security/types.py
nepse/utils.py
nepse_api-1.1.11.dist-info/LICENSE
nepse_api-1.1.11.dist-info/WHEEL
nepse_api-1.1.11.dist-info/METADATA
nepse_api-1.1.11.dist-info/RECORD
