Metadata-Version: 2.1
Name: nepse-api
Version: 1.1.11
Summary: This is a API wrapper for NEPSE API.
Home-page: https://github.com/Samrid-Pandit/nepse-api/
License: MIT
Author: Samrid Pandit
Author-email: samrid.pandit@gmail.com
Requires-Python: >=3.7,<4.0
Classifier: License :: OSI Approved :: MIT License
Classifier: Operating System :: OS Independent
Classifier: Programming Language :: Python :: 3
Classifier: Programming Language :: Python :: 3.7
Classifier: Programming Language :: Python :: 3.8
Classifier: Programming Language :: Python :: 3.9
Classifier: Topic :: Software Development :: Libraries :: Python Modules
Requires-Dist: attrs (>=21.2.0,<22.0.0)
Requires-Dist: cachetools (>=4.2.2,<5.0.0)
Requires-Dist: httpx (>=0.18.1,<0.19.0)
Requires-Dist: pyhumps (>=3.0.2,<4.0.0)
Project-URL: Repository, https://github.com/Samrid-Pandit/nepse-api/
